Workbook

Sheet Datos
A1: Caja Inicial (antes del primer mes) | B1: 30000
A3: Introduce un mes por fila. Ingresos y Gastos deben ser importes positivos.
A4: Mes (AAAA-MM) | B4: Ingresos (€) | C4: Gastos (€)
A5: 2025-07 | B5: 4200 | C5: 7100
A6: 2025-08 | B6: 3800 | C6: 6950
A7: 2025-09 | B7: 3950 | C7: 6800
A8: 2025-10 | B8: 4100 | C8: 6900
A9: 2025-11 | B9: 3900 | C9: 6850
A10: 2025-12 | B10: 4050 | C10: 6900

Sheet Cálculo 4 Pilares
A1: Cálculo de indicadores de los 4 Pilares a partir de datos mensuales agregados
A3: Mes | B3: Ingresos (€) | C3: Gastos (€) = Gross Burn Rate | D3: Net Burn Rate (€) = Gastos − Ingresos | E3: Caja Disponible (€) (acumulada) | F3: MoM Growth (%) (sobre Ingresos)
A4: =Datos!A5 | B4: =Datos!B5 | C4: =Datos!C5 | D4: =IF(Datos!A5="","",C4-B4) | E4: =IF(Datos!A5="","",Datos!$B$1+B4-C4)
A5: =Datos!A6 | B5: =Datos!B6 | C5: =Datos!C6 | D5: =IF(Datos!A6="","",C5-B5) | E5: =IF(Datos!A6="","",E4+B5-C5) | F5: =IF(OR(Datos!A6="",Datos!A5=""),"",IF(B4=0,"",(B5-B4)/B4))
A6: =Datos!A7 | B6: =Datos!B7 | C6: =Datos!C7 | D6: =IF(Datos!A7="","",C6-B6) | E6: =IF(Datos!A7="","",E5+B6-C6) | F6: =IF(OR(Datos!A7="",Datos!A6=""),"",IF(B5=0,"",(B6-B5)/B5))
A7: =Datos!A8 | B7: =Datos!B8 | C7: =Datos!C8 | D7: =IF(Datos!A8="","",C7-B7) | E7: =IF(Datos!A8="","",E6+B7-C7) | F7: =IF(OR(Datos!A8="",Datos!A7=""),"",IF(B6=0,"",(B7-B6)/B6))
A8: =Datos!A9 | B8: =Datos!B9 | C8: =Datos!C9 | D8: =IF(Datos!A9="","",C8-B8) | E8: =IF(Datos!A9="","",E7+B8-C8) | F8: =IF(OR(Datos!A9="",Datos!A8=""),"",IF(B7=0,"",(B8-B7)/B7))
A9: =Datos!A10 | B9: =Datos!B10 | C9: =Datos!C10 | D9: =IF(Datos!A10="","",C9-B9) | E9: =IF(Datos!A10="","",E8+B9-C9) | F9: =IF(OR(Datos!A10="",Datos!A9=""),"",IF(B8=0,"",(B9-B8)/B8))
A10: =Datos!A11 | B10: =Datos!B11 | C10: =Datos!C11 | D10: =IF(Datos!A11="","",C10-B10) | E10: =IF(Datos!A11="","",E9+B10-C10) | F10: =IF(OR(Datos!A11="",Datos!A10=""),"",IF(B9=0,"",(B10-B9)/B9))
A11: =Datos!A12 | B11: =Datos!B12 | C11: =Datos!C12 | D11: =IF(Datos!A12="","",C11-B11) | E11: =IF(Datos!A12="","",E10+B11-C11) | F11: =IF(OR(Datos!A12="",Datos!A11=""),"",IF(B10=0,"",(B11-B10)/B10))
A12: =Datos!A13 | B12: =Datos!B13 | C12: =Datos!C13 | D12: =IF(Datos!A13="","",C12-B12) | E12: =IF(Datos!A13="","",E11+B12-C12) | F12: =IF(OR(Datos!A13="",Datos!A12=""),"",IF(B11=0,"",(B12-B11)/B11))
A13: =Datos!A14 | B13: =Datos!B14 | C13: =Datos!C14 | D13: =IF(Datos!A14="","",C13-B13) | E13: =IF(Datos!A14="","",E12+B13-C13) | F13: =IF(OR(Datos!A14="",Datos!A13=""),"",IF(B12=0,"",(B13-B12)/B12))
A14: =Datos!A15 | B14: =Datos!B15 | C14: =Datos!C15 | D14: =IF(Datos!A15="","",C14-B14) | E14: =IF(Datos!A15="","",E13+B14-C14) | F14: =IF(OR(Datos!A15="",Datos!A14=""),"",IF(B13=0,"",(B14-B13)/B13))
A15: =Datos!A16 | B15: =Datos!B16 | C15: =Datos!C16 | D15: =IF(Datos!A16="","",C15-B15) | E15: =IF(Datos!A16="","",E14+B15-C15) | F15: =IF(OR(Datos!A16="",Datos!A15=""),"",IF(B14=0,"",(B15-B14)/B14))
A16: =Datos!A17 | B16: =Datos!B17 | C16: =Datos!C17 | D16: =IF(Datos!A17="","",C16-B16) | E16: =IF(Datos!A17="","",E15+B16-C16) | F16: =IF(OR(Datos!A17="",Datos!A16=""),"",IF(B15=0,"",(B16-B15)/B15))
... A27: =Datos!A28 | B27: =Datos!B28 | C27: =Datos!C28 | D27: =IF(Datos!A28="","",C27-B27) | E27: =IF(Datos!A28="","",E26+B27-C27) | F27: =IF(OR(Datos!A28="",Datos!A27=""),"",IF(B26=0,"",(B27-B26)/B26))
A30: Resumen — Cash Management
A31: Gross Burn Rate promedio (€/mes) | B31: =AVERAGE(C4:C27)
A32: Net Burn Rate promedio (€/mes) | B32: =AVERAGE(D4:D27)
A33: Caja Disponible (último mes, €) | B33: =LOOKUP(2,1/(E4:E27<>""),E4:E27)
A34: Tipo de métrica | B34: =IF(B32>0,"Runway (Net Burn > 0)",IF(B32=0,"Equilibrio (Net Burn = 0)","Meses de Reserva (Net Burn < 0, rentable)"))
A35: Runway / Meses de Reserva (meses) | B35: =IF(B32>0,B33/B32,IF(B32=0,"∞ (equilibrio)",B33/B31))
A37: Nota: con datos mensuales agregados (sin desglose de Categoría/Subcategoría, ID Cliente, Comercializadora, Fecha de Baja ni Fecha de Activación) solo pueden calcularse Gross Burn Rate, Net Burn Rate, Caja Disponible, Runway/Meses de Reserva (Pilar 1: Cash Management) y MoM Growth (Pilar 3: Crecimiento).

Sheet Indicadores no calculables
A1: Indicadores de los 4 Pilares que NO pueden calcularse con datos mensuales agregados
A3: Pilar | B3: Indicador | C3: Dato adicional que requeriría
A4: Eficiencia | B4: Margen de Contribución | C4: Importe de venta individual, Comisión Comercial y Coste por lead de cada venta
A5: Eficiencia | B5: CAC (Customer Acquisition Cost) | C5: Gasto de Marketing y de Venta por categoría, y nº de clientes nuevos (CANAL/NUEVO)
A6: Eficiencia | B6: LTV (Lifetime Value) | C6: Ingreso Medio por Cliente (ID Cliente) y Churn Rate, que a su vez requiere Fecha de Baja por venta
A7: Eficiencia | B7: Churn Rate | C7: ID Cliente y Fecha de Baja de cada venta
A8: Eficiencia | B8: ROI por Subcanal | C8: Gasto e ingresos desglosados por Subcanal de marketing
A9: Crecimiento | B9: Ventas por Categoría/Sector y por Canal | C9: Categoría (Energía/Telefonía/Placas Solares/Alarmas) y Canal/Subcanal de cada venta
A10: OpEx | B10: Gastos por Categoría | C10: Categoría (Personal, Marketing, Software, Oficina, etc.) de cada gasto
A11: Cash Management / Bajas | B11: % de Bajas y Bajas por Comercializadora | C11: Comercializadora y Fecha de Baja de cada venta
